pi_fan_controller/__init__.py
pi_fan_controller/fancontrol.py
pi_fan_controller-0.1.0.dist-info/METADATA
pi_fan_controller-0.1.0.dist-info/WHEEL
pi_fan_controller-0.1.0.dist-info/entry_points.txt
pi_fan_controller-0.1.0.dist-info/RECORD
