Metadata-Version: 2.4
Name: pi-fan-controller
Version: 0.1.0
Summary: Add your description here
Author-email: Jakob Guldberg Aaes <jakob1379@gmail.com>
Requires-Python: >=3.12
Requires-Dist: gpiozero>=2.0.1
Requires-Dist: rich>=13.9.4
Requires-Dist: rpi-gpio>=0.7.1
Requires-Dist: sane-rich-logging>=1.0.1
Requires-Dist: typer>=0.12.5
